ansi_text/__init__.py
ansi_text/ansi_text.py
ansi_text-1.0.1.dist-info/METADATA
ansi_text-1.0.1.dist-info/WHEEL
ansi_text-1.0.1.dist-info/licenses/LICENSE
ansi_text-1.0.1.dist-info/RECORD
