Metadata-Version: 2.1
Name: ansi_text
Version: 1.0.1
Summary: Tools for easily reading and manipulating text with formatting provided by ANSI escape sequences
Project-URL: Homepage, https://github.com/timothy-salazar/ansi_text
Project-URL: Bug Tracker, https://github.com/timothy-salazar/ansi_text/issues
Author-email: Timothy Salazar <tim@polytropos.ai>
License-File: LICENSE
Classifier: License :: OSI Approved :: MIT License
Classifier: Operating System :: OS Independent
Classifier: Programming Language :: Python :: 3
Requires-Python: >=3.7
